{
  "agent1_entities": 98,
  "agent2_entities": 74,
  "overlap": 54,
  "only_in_agent1": [
    "restaurant dar hi",
    "cafe mille colombes",
    "le relais",
    "le corail",
    "dar el bahri",
    "le grand cafe du theatre",
    "le jardin de carthage",
    "cafe des delices",
    "le dinar",
    "dar el hana",
    "le jardin de la medina",
    "restaurant sidi bou said",
    "restaurant el mouradi sousse",
    "la maison de la tradition",
    "el kantaoui",
    "dar el karama",
    "cafe de france",
    "le zitoun",
    "le restaurant de la kasbah",
    "le calypso",
    "el-khrouba",
    "le restaurant el ali",
    "le relais de hammamet",
    "le relais de la medina",
    "cafe de l'arcade",
    "dar zaytoun",
    "restaurant le grenier de hammamet",
    "el dorado",
    "la maison de la medina",
    "le petit chatelet",
    "restaurant al mina",
    "le miroir",
    "restaurant el fell",
    "cafe de l'avenue",
    "dar zitouna",
    "le bistro",
    "al farkhana",
    "el-ksar",
    "le jardin de l'atlas",
    "le baron",
    "el mouradi sousse",
    "cafe de paris",
    "dar h'mida",
    "cafe sidi bouhdid"
  ],
  "only_in_agent2": [
    "restaurant sidi mansour",
    "el mouradi gammarth",
    "tunis grand hotel",
    "dar hi life",
    "restaurant le souk",
    "el ali restaurant & cafe",
    "dar chikh cafe resto",
    "dar el andalous",
    "el mida",
    "restaurant la medina",
    "le resto du port",
    "cafe les arcades",
    "lemdina",
    "restaurant el fel",
    "dar el andalous guest house",
    "elbarkoun",
    "dar el jeld restauraunt",
    "le pirate restaurant",
    "mille mercis",
    "el zaitouna restaurant"
  ],
  "unified_rows": 99,
  "quality_complete": 44,
  "quality_partial": 27,
  "quality_agent2_failed": 28,
  "failed_entities": [
    "la kasbah",
    "le pirate",
    "dar el-andalous",
    "le calife",
    "la mamma",
    "dar h'mida",
    "le miroir",
    "dar zitouna",
    "el dorado",
    "el-khrouba",
    "dar zaytoun",
    "café sidi bouhdid",
    "el-ksar",
    "le bistro",
    "al farkhana",
    "le relais",
    "le dinar",
    "le corail",
    "café mille colombes",
    "el kantaoui",
    "le calypso",
    "le restaurant de la kasbah",
    "le baron",
    "restaurant al mina",
    "la fontaine",
    "la bougie",
    "dar el andalou",
    "le zitoun"
  ],
  "avg_data_completeness": 0.525,
  "avg_overall_confidence": 0.641,
  "ta_coverage_pct": 47.5,
  "gm_coverage_pct": 68.7,
  "wikipedia_coverage_pct": 4.0
}